ScopusApyJson/__init__.py
ScopusApyJson/api_manager.py
ScopusApyJson/json_parser.py
ScopusApyJson/json_utils.py
ScopusApyJson/main.py
ScopusApyJson/saj_globals.py
ScopusApyJson/CLI/__init__.py
ScopusApyJson/CLI/cli.py
ScopusApyJson/CONFIG/api_scopus_config.json
ScopusApyJson/CONFIG/scopus_col_names.json
ScopusApyJson-1.1.4.dist-info/LICENSE
ScopusApyJson-1.1.4.dist-info/METADATA
ScopusApyJson-1.1.4.dist-info/WHEEL
ScopusApyJson-1.1.4.dist-info/entry_points.txt
ScopusApyJson-1.1.4.dist-info/top_level.txt
ScopusApyJson-1.1.4.dist-info/RECORD
